MANIFEST.in
README.rst
setup.py
docs/HISTORY.rst
docs/INSTALL.txt
docs/LICENSE.GPL
docs/LICENSE.txt
rt/__init__.py
rt.friendlyzcatalog.egg-info/PKG-INFO
rt.friendlyzcatalog.egg-info/SOURCES.txt
rt.friendlyzcatalog.egg-info/dependency_links.txt
rt.friendlyzcatalog.egg-info/entry_points.txt
rt.friendlyzcatalog.egg-info/namespace_packages.txt
rt.friendlyzcatalog.egg-info/not-zip-safe
rt.friendlyzcatalog.egg-info/requires.txt
rt.friendlyzcatalog.egg-info/top_level.txt
rt/friendlyzcatalog/__init__.py
rt/friendlyzcatalog/configure.zcml
rt/friendlyzcatalog/patches.py
rt/friendlyzcatalog/dtml/base_catalogAdvanced.dtml
rt/friendlyzcatalog/dtml/catalogView.dtml
rt/friendlyzcatalog/dtml/plone_catalogAdvanced.dtml