Metadata-Version: 1.0
Name: rt.friendlyzcatalog
Version: 0.1.0a1
Summary: Some patches to ZCatalog UI, to make it more friendly
Home-page: http://github.com/RedTurtle/rt.friendlyzcatalog
Author: RedTurtle Technology
Author-email: sviluppoplone@redturtle.it
License: GPL
Keywords: plone zope zcatalog plonegov
Platform: UNKNOWN
Classifier: Framework :: Plone
Classifier: Framework :: Zope2
Classifier: Programming Language :: Python
